setup.py
dsnd_abdul1/Binomialdistribution.py
dsnd_abdul1/Gaussiandistribution.py
dsnd_abdul1/Generaldistribution.py
dsnd_abdul1/__init__.py
dsnd_abdul1.egg-info/PKG-INFO
dsnd_abdul1.egg-info/SOURCES.txt
dsnd_abdul1.egg-info/dependency_links.txt
dsnd_abdul1.egg-info/not-zip-safe
dsnd_abdul1.egg-info/top_level.txt