Metadata-Version: 1.0
Name: dsnd-abdul1
Version: 0.1
Summary: Gaussian and Binomial distributions
Home-page: UNKNOWN
Author: abdul
Author-email: UNKNOWN
License: UNKNOWN
Platform: UNKNOWN
